{
  "analysis": {
    "productName": "ペティオ (Petio) 猫用おもちゃ けりぐるみ エビ",
    "parentAsin": "B0DW4B6879",
    "productDescription": "またたびの実が入った、猫が抱きついて夢中で遊ぶエビの形をしたぬいぐるみです。",
    "productUsage": [
      "猫のストレス解消・運動不足解消に",
      "子猫の噛み癖・キック癖のしつけに",
      "飼い主とのコミュニケーションツールとして",
      "一人遊び用のおもちゃとして"
    ],
    "positivePoints": [
      "またたび入りで多くの猫が強い興味を示す",
      "猫が抱きつきやすい細長い形状",
      "丈夫なコットン生地でできており、激しい遊びにも耐えやすい",
      "手頃な価格でコストパフォーマンスが高い",
      "子猫の甘噛みやキックの対象を人の手足から逸らすのに役立つ"
    ],
    "negativePoints": [
      "またたびの効果に個体差があり、全く興味を示さない猫もいる",
      "遊び始めてすぐに飽きてしまう場合がある",
      "激しく遊ぶと縫い目がほつれたり、中の綿が出てきたりすることがある",
      "唾液で濡れると汚れが目立ちやすく、洗濯が推奨される"
    ],
    "useCases": [
      "子猫が人の手や足に噛み付いたりキックしたりし始めた際のしつけ用として",
      "留守番中など、猫が一人で過ごす時間の退屈しのぎに",
      "新しい環境に慣れない猫のストレスを和らげるために",
      "多頭飼いの場合、おもちゃの取り合いで運動を促すきっかけに"
    ],
    "userStories": [
      {
        "userType": "3ヶ月の子猫の飼い主",
        "scenario": "人の腕にキックをし始めたため、代わりになるおもちゃを探していた",
        "experience": "商品を渡した途端、ものすごく気に入り、カジカジしたりキックしたりして激しく遊び始めた。人の腕へのキックが減り、エビのぬいぐるみと戦う姿がとても可愛らしくて満足している。",
        "sentiment": "positive"
      },
      {
        "userType": "マンチカンの飼い主",
        "scenario": "猫が抱きかかえて蹴って遊ぶことを期待して購入",
        "experience": "残念ながら、うちの猫は匂いを嗅ぐだけでほとんど興味を示さなかった。期待していたような遊び方は一度も見られなかったが、商品のデザインや作りの丈夫さは良いと感じた。",
        "sentiment": "mixed"
      },
      {
        "userType": "シンガプーラの飼い主",
        "scenario": "猫の新しいおもちゃとして購入",
        "experience": "箱から出した途端に興味を示し、30分以上も噛んだり蹴ったりして遊び続けた。激しく遊びすぎて爪（ヒゲの部分）が取れてしまったが、縫い付けて修理したらまた戦いに行った。買ってよかった。",
        "sentiment": "positive"
      },
      {
        "userType": "ラガマフィンの飼い主",
        "scenario": "SNSで人気なのを見て、またたび入りなら気に入るだろうと思い購入",
        "experience": "なぜか全く興味を示さず、完全に無視されてしまった。商品は可愛いのにとても残念。寝ている猫の 옆にそっと置いて写真を撮るくらいしかできなかった。",
        "sentiment": "negative"
      }
    ],
    "userImpression": "多くの猫が夢中になる「当たり」のおもちゃとして評価が高い。特に、子猫の有り余るエネルギーを発散させたり、噛み癖を直したりするのに非常に効果的だという声が多い。またたびの効果と抱きつきやすい形状が猫の本能を刺激するようだ。一方で、またたびへの反応には個体差があるため、全く興味を示さない猫もおり、その場合は期待外れに終わる。消耗品と割り切って購入するユーザーが多く、価格の安さもあって総合的な満足度は高い。",
    "sources": [
      {
        "name": "みんなのペット健康専門店 お客様の声・レビュー",
        "url": "https://www.min-petkenko.com/goodsReviewList.php?goods_id=petio_85&sort=Usefulness",
        "credibility": "高"
      },
      {
        "name": "Amazon PA-API 商品情報",
        "url": null,
        "credibility": "高"
      }
    ],
    "lastInvestigated": "2026-01-10",
    "competitiveAnalysis": [
      {
        "name": "またたびトイ",
        "asin": "B0CZD1KCS5",
        "priceComparison": "約950円と、本製品（約636円）より高価。",
        "featureComparison": [
          "こちらはスプレータイプで、既存のおもちゃや爪とぎに吹きかけて使用する。",
          "ぬいぐるみ自体がおもちゃになる本製品とは用途が異なる。"
        ],
        "differentiators": [
          "ぬいぐるみと異なり、様々なおもちゃにまたたび効果を付与できる。",
          "消費アイテムであり、定期的な購入が必要になる可能性がある。"
        ]
      },
      {
        "name": "ミュー (mju:) 猫用おもちゃ ニャンコロビー ボックス",
        "asin": "B01LZDJA8J",
        "priceComparison": "約1,876円と、本製品より大幅に高価。",
        "featureComparison": [
          "爪とぎとボールが一体になったおもちゃ。",
          "猫が中に入って遊ぶことができ、けりぐるみとは異なる遊び方を提供する。"
        ],
        "differentiators": [
          "爪とぎ機能があり、複数の機能を持つ。",
          "サイズが大きく、設置場所が必要。"
        ]
      },
      {
        "name": "YABALA 猫じゃらし",
        "asin": "B09MFGCTL8",
        "priceComparison": "約3,379円と非常に高価。",
        "featureComparison": [
          "飼い主が手に持って猫と遊ぶタイプの「猫じゃらし」。",
          "猫が一人で遊ぶ「けりぐるみ」とは遊び方が異なる。"
        ],
        "differentiators": [
          "飼い主とのインタラクティブな遊びに特化している。",
          "価格が高く、単純なぬいぐるみとは異なるカテゴリの商品。"
        ]
      }
    ],
    "recommendation": {
      "targetUsers": [
        "エネルギーがあり余っている若い猫や子猫の飼い主",
        "猫の噛み癖やキック癖に悩んでいる飼い主",
        "手頃な価格で猫が喜ぶおもちゃを探している人",
        "留守番など、猫が一人で遊ぶためのおもちゃを探している人"
      ],
      "pros": [
        "コストパフォーマンスが非常に高い",
        "多くの猫の狩猟本能を刺激し、夢中にさせる力がある",
        "丈夫な素材で長持ちしやすい",
        "猫のストレス解消や運動不足解消に効果的"
      ],
      "cons": [
        "猫によっては全く興味を示さないリスクがある",
        "耐久性には限界があり、いずれは壊れる消耗品である",
        "唾液で汚れやすく、衛生管理が必要"
      ],
      "score": 82,
      "scoreRationale": "[基本点: 70]\n[加点: +15] (圧倒的なコストパフォーマンスと、多くの猫を夢中にさせる実績)\n[加点: +5] (子猫のしつけや問題行動の改善に役立つという実用性)\n[減点: -5] (猫による興味の個体差が大きく、全く遊ばないリスクがあるため)\n[減点: -3] (消耗品であり、激しく遊ぶと破損する可能性があるため)\n[合計: 82]"
    },
    "technicalSpecs": {
        "material": {
            "fabric": "コットン",
            "filling": "ポリエステル、またたびの実"
        },
        "dimensions": {
            "height": "約33cm",
            "width": "約10cm",
            "depth": "約7cm",
            "weight": "約70g"
        },
        "targetSpecies": "全猫種",
        "countryOfOrigin": "中国",
        "other": ["またたび入り"]
    }
  }
}