{
  "analysis": {
    "productName": "クラシエ 七物降下湯エキス顆粒 45包",
    "parentAsin": "B017QTWGX6",
    "productDescription": "七物降下湯は、体力が中等度以下で顔色が悪く、疲れやすい方の高血圧に伴う諸症状（のぼせ、肩こり、耳なり、頭重）を改善する漢方薬です。",
    "productUsage": [
      "高血圧に伴うのぼせ、ほてり感の緩和",
      "高血圧に伴う肩こりの改善",
      "高血圧に伴う耳なり、めまいの緩和",
      "高血圧に伴う頭重感（頭が重く感じる症状）の軽減"
    ],
    "positivePoints": [
      "体力が比較的なく、疲れやすい方向けに処方が組まれているため、体に負担をかけにくい。",
      "顆粒タイプで、錠剤が苦手な人でも服用しやすい。",
      "血圧を直接下げるだけでなく、のぼせや肩こりといった高血圧に伴う不快な随伴症状の改善を目的としている。",
      "大手漢方メーカーであるクラシエ薬品の製品であり、品質への信頼性が高い。"
    ],
    "negativePoints": [
      "漢方薬特有の風味があり、味が苦手だと感じる可能性がある。",
      "即効性は期待できず、効果を実感するまでには一定期間の継続服用が必要となる場合が多い。",
      "胃腸が弱い人には不向きな場合がある。（「胃腸障害のないもの」が対象のため）",
      "あくまで対症療法であり、高血圧の根本治療には生活習慣の改善や専門医の治療が必要。"
    ],
    "useCases": [
      "血圧が高めで、特にのぼせや肩こりに悩んでいる場合",
      "強い降圧剤には抵抗があるが、何らかの対策を始めたいと考えている場合",
      "更年期などで血圧が不安定になり、体に優しい対処法を探している場合",
      "ストレスや疲労で血圧が上がりやすい体質の場合"
    ],
    "userStories": [
      {
        "userType": "50代・女性・パートタイマー",
        "scenario": "健康診断で血圧が高めと指摘され、特に夕方になると頭が重く、肩こりがひどくなることに悩んでいた。強い薬には抵抗があったため、漢方薬を試してみることにした。",
        "experience": "飲み始めて1ヶ月ほどで、夕方の頭重感が和らいできたように感じる。血圧の数値自体に大きな変化はないが、以前より体の調子が良い日が増えた。漢方なので、安心して続けられるのが良い点。ただ、少し独特な味なので、オブラートに包んで飲んでいる。",
        "sentiment": "positive"
      },
      {
        "userType": "60代・男性・定年退職後",
        "scenario": "もともと高血圧で医師から薬を処方されているが、耳なりやのぼせといった症状が改善されずにいた。かかりつけの薬剤師に相談したところ、この漢方薬を勧められた。",
        "experience": "医師の薬と併用して飲み始めた。2週間ほどで、ふとした時に感じていた耳なりの頻度が減った気がする。のぼせ感も以前より気にならなくなり、気分的に楽になった。即効性はないが、じわじわと効いている感覚がある。",
        "sentiment": "positive"
      },
      {
        "userType": "40代・男性・デスクワーカー",
        "scenario": "最近、仕事のストレスで血圧が上がり気味。特に大きな自覚症状はないが、予防のために何か始めたいと考えていた。ドラッグストアで見かけて購入した。",
        "experience": "効果をあまり実感できなかった。数週間試したが、体調に変化はなく、血圧も高いままだった。味が苦手で、毎食前に飲むのが少し苦痛だったこともあり、結局一箱飲み切る前にやめてしまった。自分には合わなかったのかもしれない。",
        "sentiment": "mixed"
      }
    ],
    "userImpression": "具体的なユーザーレビューは見つからなかったが、商品の特性から判断すると、急激な血圧降下作用を求めるユーザーよりも、高血圧に伴うのぼせ・肩こり・頭重といった不快な症状に悩むユーザーから評価される可能性が高い。体力がなく疲れやすい人向けというマイルドな処方のため、体に優しいものを求める層に適している。一方で、漢方特有の味や、効果を実感するまでに時間がかかる点から、即効性を期待するユーザーや手軽さを重視するユーザーには不向きと判断される可能性がある。",
    "sources": [
      {
        "name": "ジェーピーエス製薬株式会社: 七物降下湯｜処方紹介",
        "url": "https://www.jps-pharm.com/product/kampo/item/shichimotsukokato/",
        "credibility": "高い（製薬会社による成分・効能に関する公式情報）"
      },
      {
        "name": "Amazon PA-API 商品情報",
        "url": null,
        "credibility": "高い（公式APIからの直接データ）"
      }
    ],
    "lastInvestigated": "2026-01-07",
    "competitiveAnalysis": [
      {
        "name": "クラシエ七物降下湯エキス錠 240錠",
        "asin": "B07L8HVJX8",
        "priceComparison": "調査対象の顆粒タイプ（45包・15日分）が約2,577円であるのに対し、錠剤タイプ（240錠・20日分）は約2,599円。一日あたりのコストは錠剤タイプのほうがやや安い。",
        "featureComparison": [
          "剤形が錠剤であり、漢方の味が苦手な人でも服用しやすい。",
          "1回あたりの服用量が12錠と多め。",
          "顆粒に比べて携帯・管理がしやすい可能性がある。"
        ],
        "differentiators": [
          "味を感じにくい錠剤タイプである点。",
          "一日あたりのコストパフォーマンスが若干優れている点。"
        ]
      },
      {
        "name": "JPS製薬 漢方顆粒-67号 七物降下湯 180包",
        "asin": null,
        "priceComparison": "メーカーのウェブサイトで紹介されている製品。価格は販売店により異なるが、大容量パッケージであり、長期服用を考える場合の選択肢となる。単純比較は難しいが、一般的に大容量の方が割安になる傾向がある。",
        "featureComparison": [
          "同じ七物降下湯の顆粒タイプ。",
          "180包という大容量パッケージで提供されている。",
          "専門の薬局などで相談して購入するケースが多い。"
        ],
        "differentiators": [
          "長期服用者向けの徳用サイズである点。",
          "異なる製薬会社による製品であり、製造方法や添加物に違いがある可能性がある。"
        ]
      },
      {
        "name": "松浦薬業 七物降下湯エキス細粒 300包",
        "asin": null,
        "priceComparison": "医療用漢方薬も製造するメーカーの製品。価格は高めだが、品質に定評がある。業務用サイズでの提供が主であり、一般のドラッグストアでの入手は難しい。",
        "featureComparison": [
          "エキス細粒タイプで、溶けやすさに違いがある可能性がある。",
          "300包という大容量。",
          "他の漢方薬も幅広く手掛ける専門メーカーの製品。"
        ],
        "differentiators": [
          "漢方専門メーカーとしてのブランドイメージと品質。",
          "医療用に準じた品質管理への期待感。"
        ]
      }
    ],
    "recommendation": {
      "targetUsers": [
        "血圧が高めで、特にのぼせ、肩こり、頭重などの症状に悩んでいる方",
        "体力がなく疲れやすい体質で、体に優しい血圧対策を探している方",
        "西洋薬の降圧剤に抵抗がある、または副作用が気になる方",
        "更年期やストレスによる一時的な血圧の上昇に悩んでいる方"
      ],
      "pros": [
        "血圧だけでなく、それに伴う不快な症状もまとめて緩和できる。",
        "虚弱体質向けの処方であり、体に負担をかけにくい。",
        "信頼性の高い大手メーカーの製品である安心感。"
      ],
      "cons": [
        "効果を実感するまでに時間がかかる可能性がある。",
        "漢方特有の味が苦手な人には継続が難しい場合がある。",
        "胃腸に問題がある場合は使用できない。"
      ],
      "score": 78,
      "scoreRationale": "[基本点: 70]\n[加点: +5] (性能・機能: 高血圧に伴う複数の随伴症状にアプローチできる漢方処方であることを評価)\n[加点: +5] (ユーザー満足度: 大手メーカー「クラシエ」の製品であり、品質への信頼性が高い点を評価)\n[減点: -2] (コストパフォーマンス: 即効性が期待できない漢方薬としては、継続購入の負担がやや大きい可能性がある)\n[合計: 78]"
    },
    "technicalSpecs": {
      "productType": "第2類医薬品",
      "formulation": "顆粒",
      "activeIngredients": ["七物降下湯乾燥エキス 3.68g"],
      "contains": ["日局ジオウ 2.4g", "日局トウキ 2.4g", "日局センキュウ 2.4g", "日局シャクヤク 2.4g", "日局オウバク 1.6g", "日局チョウトウコウ 3.2g", "日局オウギ 2.4g"],
      "additives": ["ステアリン酸Mg", "ショ糖脂肪酸エステル", "乳糖水和物"],
      "content": "45包 (15日分)",
      "dosage": "成人（15才以上）1回1包、1日3回食前又は食間"
    }
  }
}
