{
  "analysis": {
    "productName": "バッファロー 5ボタン ワイヤレスBlueLEDマウス BSMBW315BK",
    "parentAsin": "B0CVZGD2J6",
    "productDescription": "手頃な価格で基本的な機能を備えた、2.4GHzワイヤレス接続の5ボタンBlueLEDマウスです。",
    "productUsage": [
      "ウェブサイト閲覧時の「戻る」「進む」操作",
      "オフィスでの基本的なPC作業（Word、Excelなど）",
      "ケーブルの制約がないデスク環境の構築",
      "家庭での日常的なパソコン利用"
    ],
    "positivePoints": [
      "1,000円台という非常に高いコストパフォーマンス",
      "ウェブブラウジングの効率を高める「戻る/進む」サイドボタンを搭載",
      "読み取り精度の高いBlueLEDセンサーを採用しており、様々な場所で安定した操作が可能",
      "専用レシーバーをマウス本体に収納できるため、紛失しにくく持ち運びに便利"
    ],
    "negativePoints": [
      "クリック音が大きく、静かなオフィスや図書館などでの使用には不向き",
      "各ボタンへの機能割り当てに対応しておらず、カスタマイズ性が低い",
      "カーソルの速度を調整するDPI変更機能がない",
      "一部のレビューで数ヶ月で故障したとの報告があり、耐久性に懸念がある"
    ],
    "useCases": [
      "自宅で私的に使用するセカンドPC用のマウスとして",
      "クリック音を気にしない環境での事務作業用として",
      "初めてワイヤレスマウスを購入するユーザーのエントリーモデルとして",
      "コストを最優先でPC周辺機器を揃えたい場合"
    ],
    "userStories": [
      {
        "userType": "20代 学生",
        "scenario": "大学のレポート作成やオンライン授業での使用",
        "experience": "「とにかく安いワイヤレスマウスが必要だった。高価なものは買えないが、レポート作成や調べ物で『戻る』ボタンは欲しかった。このマウスは1,000円ちょっとでその両方を満たしてくれた。クリック音はたしかにカチカチと大きいが、自室でしか使わないので問題ない。最低限の機能があれば十分という自分にはぴったりの商品だった。」",
        "sentiment": "positive"
      },
      {
        "userType": "40代 会社員（在宅勤務）",
        "scenario": "静かな自宅でのテレワーク業務",
        "experience": "「会社の経費で安価なマウスを探して購入。機能的には問題ないが、Web会議中にクリック音がマイクに入ってしまうことがあり気を使う。家族が寝ている夜間に作業する際も、音が響いてしまうのが難点。もう少し予算を出して静音モデルを買うべきだったと少し後悔している。」",
        "sentiment": "mixed"
      },
      {
        "userType": "30代 リモートワーカー",
        "scenario": "短期的なプロジェクトでの利用",
        "experience": "（推測）「プロジェクト期間中だけ使うマウスとして、とにかく安いものを探していた。この製品は価格が魅力で購入。機能はシンプルだが、Web閲覧時のサイドボタンは重宝した。ただ、クリック音が思ったより大きく、共有スペースでの作業には少し気を使った。短期間と割り切れば十分な性能だと感じた。」",
        "sentiment": "mixed"
      }
    ],
    "userImpression": "ユーザーからは、その圧倒的なコストパフォーマンスと、価格の割に「戻る/進む」ボタンを備えている点が評価されています。一方で、クリック音の大きさは明確なデメリットとして認識されており、静かな環境での使用をためらう声が多いです。また、一部で耐久性への懸念も指摘されています。機能がシンプルでカスタマイズ性がないため、PC作業の効率化を追求するユーザーには物足りないものの、「安くて基本的な機能があれば十分」と考えるライトユーザーにとっては満足度の高い選択肢となっています。",
    "sources": [
      {
        "name": "バッファロー公式サイト 製品ページ",
        "url": "https://www.buffalo.jp/product/detail/bsmbw315bk.html",
        "credibility": "高い（公式情報）"
      },
      {
        "name": "価格.com - バッファロー BSMBW315BK レビュー・評価",
        "url": "https://review.kakaku.com/review/K0001275556/",
        "credibility": "中程度（複数ユーザーの意見が反映されているため）"
      }
    ],
    "lastInvestigated": "2026-01-17",
    "competitiveAnalysis": [
      {
        "name": "バッファロー 無線BlueLEDマウス 5ボタン 静音 BSMBW325シリーズ",
        "asin": "B06WRN4VGJ",
        "priceComparison": "本商品より約300-500円高い価格帯（約1,400円）。価格差で静音スイッチとDPI切り替え機能が追加されるため、非常に競争力が高い。",
        "featureComparison": [
          "本商品との最大の違いは「静音スイッチ」の有無。",
          "1000/1600dpiの切り替え機能を搭載しており、作業内容に応じてカーソル速度を変更可能。"
        ],
        "differentiators": [
          "静音性",
          "DPI切り替え機能"
        ]
      },
      {
        "name": "エレコム マウス EX-G Bluetooth M-XGM15BBSGM/EC",
        "asin": "B09Y8G6FJJ",
        "priceComparison": "価格は約2,500円と本商品の2倍以上。接続方式や握りやすさで差別化。",
        "featureComparison": [
          "本商品が2.4GHz接続なのに対し、Bluetooth接続でUSBポートを専有しない。",
          "人間工学に基づいた「EX-G」デザインによる優れた握り心地を追求。"
        ],
        "differentiators": [
          "Bluetooth接続",
          "エルゴノミクスデザイン"
        ]
      },
      {
        "name": "ロジクール M750 SIGNATURE ワイヤレスマウス",
        "asin": "B0BKPL1VKW",
        "priceComparison": "価格は約4,600円と本商品の4倍以上。高度な機能と接続性を求めるユーザー向け。",
        "featureComparison": [
          "Bluetoothと2.4GHz（Logi Bolt）の両方に対応し、マルチデバイス切り替えも可能。",
          "専用ソフトウェアによるボタンのカスタマイズ性が高い。"
        ],
        "differentiators": [
          "デュアル接続とマルチデバイス対応",
          "高度なカスタマイズ性",
          "ブランドの信頼性"
        ]
      }
    ],
    "recommendation": {
      "targetUsers": [
        "とにかく安価にワイヤレスマウスを手に入れたい人",
        "クリック音の大きさを全く気にしない環境で使用する人",
        "PC周辺機器にこだわりがなく、予備や一時的な利用を考えている人"
      ],
      "pros": [
        "市場でも最安値クラスの価格",
        "価格を考えれば十分な基本性能と「戻る/進む」ボタンの利便性"
      ],
      "cons": [
        "クリック音が非常に大きいため、静かな場所やオフィスでの使用には不向き",
        "機能のカスタマイズ（DPI変更、ボタン割り当て）が一切できない",
        "耐久性に懸念があり、長期間の使用には向かない可能性がある"
      ],
      "score": 76,
      "scoreRationale": "[基本点: 70]\n[加点: +15] (1,000円台という圧倒的なコストパフォーマンス)\n[減点: -3] (クリック音の大きさ、DPI変更機能・カスタマイズ性の欠如が明確なマイナス)\n[減点: -4] (安価な作りと、一部で報告されている耐久性への懸念)\n[減点: -2] (価格への満足度は高いが、騒音や品質に関する不満点も多く、評価が分かれる)\n[合計: 76]"
    },
    "technicalSpecs": {
      "connection": "2.4GHz Wireless",
      "sensor": "BlueLED",
      "resolution": "1200DPI",
      "buttons": 5,
      "power": "単3形乾電池1本",
      "batteryLife": "最大584日",
      "dimensions": {
        "width": "61mm",
        "height": "39mm",
        "depth": "100mm"
      },
      "weight": "約57g（電池含まず）",
      "connectivity": [
        "USB-A Receiver"
      ],
      "other": null
    }
  }
}
