
{
  "analysis": {
    "productName": "無印良品 ワーキングアームチェア (2023)",
    "parentAsin": "B0BN1NVL59",
    "productDescription": "無印良品のワーキングアームチェアは、シンプルで圧迫感のないデザインが特徴の、家庭やオフィス向けのワークチェアです。背もたれに通気性の良いメッシュ素材を採用し、快適な座り心地を提供します。",
    "productUsage": [
      "在宅ワーク・テレワークでのデスク作業",
      "リビングでの軽作業や学習",
      "書斎や子供部屋の勉強椅子",
      "オフィスの会議室や共有スペース"
    ],
    "positivePoints": [
      "適度な硬さのクッションと背もたれのフィット感が良く、座り心地が快適",
      "無印良品らしいシンプルでミニマルなデザインで、どんなインテリアにも馴染みやすい",
      "1万円を切る価格設定で、コストパフォーマンスが非常に高い",
      "背もたれがメッシュ素材のため通気性が良く、夏場でも蒸れにくい",
      "座面が広く、ゆったりと座ることができる"
    ],
    "negativePoints": [
      "長時間のデスクワークでは疲れやすいとの意見があり、8時間以上の連続使用には不向き",
      "前傾姿勢をサポートする機能がなく、作業時のホールド感は限定的",
      "ロッキング機能の固定や強弱調整がスムーズに行えない場合がある",
      "ミドルバックのため、首や肩まで支えるリラックス機能はない"
    ],
    "useCases": [
      "数時間程度の在宅ワークを行うユーザー",
      "デザイン性を重視し、リビングに置いても違和感のないワークチェアを探しているユーザー",
      "学生や子供の学習用の椅子として",
      "長時間座り続けない軽作業用のオフィスチェアとして"
    ],
    "userStories": [
      {
        "userType": "30代 在宅ワーカー",
        "scenario": "週に2〜3日の在宅勤務のために、手頃でデザインの良い椅子を探していた。",
        "experience": "（推測）無印良品のブランドイメージと価格に惹かれて購入。リビングに置いてもインテリアを邪魔しないデザインに満足している。1〜2時間の会議や作業では快適だが、一日中座っていると夕方には腰が少し疲れると感じる。ただ、毎日8時間座るわけではないので、コストとデザインのバランスを考えれば十分満足できる買い物だった。",
        "sentiment": "mixed"
      },
      {
        "userType": "大学生",
        "scenario": "オンライン授業やレポート作成のために、自室で使う椅子が必要になった。",
        "experience": "（推測）組み立ては少し手間だったが、説明書が分かりやすく一人で完成できた。座面が広く、あぐらをかきながらリラックスして使える点が気に入っている。メッシュの背もたれも快適。長時間の勉強では時々立ち上がって休憩を入れるようにしているが、特に大きな不満はない。友達にも勧められる価格だと思う。",
        "sentiment": "positive"
      }
    ],
    "userImpression": "手頃な価格と無印良品らしいシンプルなデザインが高く評価されている一方で、本格的な長時間作業には向かないという意見も見られる。短時間・断続的な使用や、デザイン性を重視するユーザーにとっては非常にコストパフォーマンスの高い選択肢と言える。",
    "sources": [
      {
        "name": "mybest: 無印良品 ワーキングアームチェア 背メッシュをレビュー！クチコミ・評判をもとに徹底検証",
        "url": "https://my-best.com/products/534384",
        "credibility": "複数のモニターによる実使用レビューと専門家の評価に基づいており、信頼性は高い"
      }
    ],
    "lastInvestigated": "2026-01-16",
    "competitiveAnalysis": [
      {
        "name": "タンスのゲン オフィスチェア",
        "asin": "B00YQW38O8",
        "priceComparison": "約7,000円と、無印良品よりさらに低価格。",
        "featureComparison": [
          "腰を支えるランバーサポートを搭載している。",
          "床を傷つけにくいPUキャスターを採用。"
        ],
        "differentiators": [
          "価格の安さと腰サポート機能が強みだが、デザインのシンプルさでは無印良品が優れる。"
        ]
      },
      {
        "name": "Supzmg オフィスチェア",
        "asin": "B0FCS18W8J",
        "priceComparison": "約9,000円で、無印良品とほぼ同価格帯。",
        "featureComparison": [
          "収納式フットレストやリクライニング機能を搭載。",
          "ハイバック仕様で頭まで支えることができる。"
        ],
        "differentiators": [
          "多機能性とリラックス性能で差別化を図っているが、その分デザインは複雑になる。"
        ]
      },
      {
        "name": "FelixKing デスクチェア",
        "asin": "B0DHCZ7TGN",
        "priceComparison": "価格情報は取得できなかったが、類似モデルは1万円前後。",
        "featureComparison": [
          "あぐらをかけるほど座面が広いのが特徴。",
          "肘掛けがなく、デスクへの収納や動きの自由度が高い。"
        ],
        "differentiators": [
          "座面の広さと肘掛けなしのユニークな設計で、特定のユーザー層（あぐらをかきたい人）に訴求している。"
        ]
      }
    ],
    "recommendation": {
      "targetUsers": [
        "1日数時間程度の在宅ワークを行う方",
        "インテリアに馴染むシンプルなデザインの椅子を探している方",
        "コストパフォーマンスを重視する学生や新社会人",
        "セカンドチェアや来客用の椅子として"
      ],
      "pros": [
        "優れたコストパフォーマンス",
        "シンプルで飽きのこないデザイン",
        "通気性の良いメッシュバック",
        "広々とした座面"
      ],
      "cons": [
        "長時間の使用には向かず、腰へのサポートが弱い",
        "調整機能が限定的で、ロッキングの操作性に難あり",
        "本格的なエルゴノミクスチェアほどの快適性はない"
      ],
      "score": 80,
      "scoreRationale": "[基本点: 70]\n[加点: +12] (1万円を切る価格でこの品質とデザインは非常にコストパフォーマンスが高い)\n[加点: +4] (無印良品らしいシンプルでインテリアに馴染むデザイン)\n[減点: -4] (基本的な座り心地は良いが、長時間の快適性や調整機能に欠ける)\n[減点: -2] (短時間利用者には好評だが、長時間の使用では疲れやすいという意見もある)\n[合計: 80]"
    },
    "technicalSpecs": {
        "dimensions": {
            "width": "64cm",
            "depth": "66cm",
            "height": "89-98.5cm",
            "seatHeight": "43-53.5cm",
            "seatWidth": "49cm",
            "seatDepth": "49cm",
            "weight": "11.2kg"
        },
        "materials": {
            "backFrame": "ポリプロピレン",
            "seat": "合板",
            "mechanism": "金属(鋼)",
            "armrest": "ナイロン、ポリウレタン",
            "base": "ナイロン",
            "casters": "ナイロン",
            "cushion": "ウレタンフォーム",
            "upholstery": "ポリエステル100%"
        },
        "features": {
            "heightAdjustment": "ガススプリング式",
            "rockingFunction": "背座一体型ロッキング",
            "armrestAdjustment": "4段階高さ調節、取り外し可能",
            "lumbarSupport": null,
            "headrest": null
        },
        "assembly": {
            "required": true,
            "toolsIncluded": ["六角レンチ"]
        },
        "origin": "中国",
        "other": ["塗装・接着剤はF☆☆☆☆等級"]
    }
  }
}
