{
  "analysis": {
    "productName": "槌屋ヤック トヨタ 50系 RAV4専用 スマートフォンホルダー SY-RA4",
    "parentAsin": "B0DFWRZF8J",
    "productDescription": "トヨタ 50系 RAV4のインテリアに純正品のようにフィットする、車種専用設計のスマートフォンホルダーです。",
    "productUsage": [
      "スマートフォンのナビゲーションアプリをカーナビとして利用する",
      "ハンズフリー通話や、音楽再生時の画面操作を安全に行う",
      "運転の視界を妨げずにスマートフォンを最適な位置に固定する"
    ],
    "positivePoints": [
      "車種専用設計による完璧なフィット感と、純正品のような一体感を実現している点。",
      "運転の視界を妨げず、視認性と操作性に優れた最適な位置へ設置できる点。",
      "両面テープや吸盤式と異なり、ぐらつきのない高い安定性と固定力を誇る点。"
    ],
    "negativePoints": [
      "ワイヤレス充電機能（Qi）や電動式の自動開閉アームといった付加機能は搭載されていない点。",
      "多機能な汎用品と比較すると、機能がシンプルな割に価格がやや高めである点。"
    ],
    "useCases": [
      "スマートフォンのナビアプリをカーナビとして利用するシーン。",
      "長距離ドライブ中に音楽を再生したり、ハンズフリー通話を行ったりするシーン。",
      "内装の見た目を損なわずに、スマートフォンをスマートに設置したい場合。"
    ],
    "userStories": [
      {
        "userType": "40代 RAV4オーナー、ドライブ好き",
        "scenario": "これまで汎用のスマホホルダーを使っていたが、夏場の熱で両面テープが剥がれたり、走行中の振動でスマートフォンが傾いたりと不満があった。特にカーブの多い山道では安定性に欠けていた。",
        "experience": "この商品に変えてから、まるで純正パーツのようにコンソールにフィットし、全くぐらつかなくなった。視界を遮らない位置にスマートフォンを固定できるため、ナビの確認が安全かつスムーズになり、運転への集中力が高まった。見た目のスマートさにも大変満足しており、ドライブがさらに快適になった。",
        "sentiment": "positive"
      }
    ],
    "userImpression": "ユーザーは「車種専用設計」がもたらす完璧なフィット感とデザインの一体性を最も高く評価している。ワイヤレス充電のような先進機能はないものの、スマートフォンを「確実に、美しく固定する」という中核機能において絶大な信頼を得ている。不安定な汎用品に不満を持つRAV4オーナーにとって、「最初からこれを買っておけば間違いない」決定版と見なされている。",
    "sources": [
      {
        "name": "トヨタ RAV4 スマホ・携帯ホルダーの口コミ・評価・レビュー - みんカラ",
        "url": "https://minkara.carview.co.jp/car/toyota/rav4/partsreview/review.aspx?bi=23&ci=844",
        "credibility": "ユーザーによる実体験レビューが多数掲載されており、信頼性は高い。"
      }
    ],
    "lastInvestigated": "2026-01-03",
    "competitiveAnalysis": [
      {
        "name": "AXIS-PARTS マグネット式 スマートフォンホルダー",
        "asin": null,
        "priceComparison": "同等か、LEDライトなどの付加機能によってはやや高価。",
        "featureComparison": [
          "マグネットによる簡単な着脱が可能。",
          "車種専用設計でフィット感は良好。"
        ],
        "differentiators": [
          "スマートフォンの着脱が片手で素早く行える利便性。",
          "一部商品にはLEDイルミネーション機能があり、夜間の車内を装飾できる。"
        ]
      },
      {
        "name": "ペルシード 自動開閉ワイヤレス充電ホルダー",
        "asin": "B08XQ7Q42Q",
        "priceComparison": "ワイヤレス充電や自動開閉機能を搭載しているため、本商品より高価。",
        "featureComparison": [
          "Qi規格のワイヤレス充電に対応。",
          "赤外線センサーによるアームの自動開閉機能。"
        ],
        "differentiators": [
          "乗車してスマートフォンを置くだけで充電とホールドが完了する利便性。",
          "先進的な機能が好きなユーザー層に訴求する。"
        ]
      },
      {
        "name": "カーメイト(CAR MATE) スマホルダー SA38",
        "asin": "B09Y1Q88ZY",
        "priceComparison": "汎用品であるため、本商品よりも安価。",
        "featureComparison": [
          "エアコン吹き出し口などに取り付ける汎用タイプ。",
          "多くの車種やスマートフォンに対応するが、専用品ほどの固定力はない。"
        ],
        "differentiators": [
          "低価格で導入できるコストパフォーマンス。",
          "車を乗り換えても使い続けられる汎用性の高さ。"
        ]
      }
    ],
    "recommendation": {
      "targetUsers": [
        "RAV4 (50系) オーナーで、車の内装との一体感を何よりも重視する人。",
        "過去に汎用ホルダーの安定性（ぐらつき、落下）や見た目に不満を感じた経験がある人。",
        "スマートフォンの基本的な固定機能（ナビ利用など）を確実に果たせれば十分だと考える人。"
      ],
      "pros": [
        "純正品と見紛うほどの完璧なフィット感と、後付け感のない高いデザイン性。",
        "悪路走行中でもスマートフォンが全くぐらつかない、圧倒的な安定性とホールド力。",
        "取り付けが非常に簡単で、工具なども一切不要な点。"
      ],
      "cons": [
        "Qiワイヤレス充電やアームの自動開閉といった便利な付加機能は一切ない点。",
        "車種専用設計のため、将来的にRAV4以外の車に乗り換えた際に流用できない点。"
      ],
      "score": 85
    }
  }
}
